Metadata-Version: 2.1
Name: carbonium
Version: 0.10.4
Summary: Manage a list of names with several properties and (overlapping) order criteria
Home-page: https://github.com/pietrogiuffrida/carbonium/
Author: Pietro Giuffrida
Author-email: pietro.giuffri@gmail.com
License: MIT
Platform: UNKNOWN
Classifier: Programming Language :: Python :: 3
Classifier: License :: OSI Approved :: MIT License
Classifier: Operating System :: OS Independent
